django_auto_models/__init__.py
django_auto_models/locale/ja/LC_MESSAGES/django.mo
django_auto_models/locale/ja/LC_MESSAGES/django.po
django_auto_models/models/__init__.py
django_auto_models/models/datetime.py
django_auto_models/models/id.py
django_auto_models-1.0.1.dist-info/METADATA
django_auto_models-1.0.1.dist-info/WHEEL
django_auto_models-1.0.1.dist-info/licenses/LICENSE
django_auto_models-1.0.1.dist-info/RECORD
