Metadata-Version: 2.1
Name: django-auto-models
Version: 1.0.1
Summary: Models with auto input fields for Django
Project-URL: Homepage, https://github.com/taogya/DjangoAutoModels
Project-URL: Bug Tracker, https://github.com/taogya/DjangoAutoModels/issues
Author-email: Taogya <132679709+taogya@users.noreply.github.com>
License: BSD 3-Clause License
License-File: LICENSE
Classifier: License :: OSI Approved :: BSD License
Classifier: Programming Language :: Python :: 3
Requires-Python: >=3.9
